vizzy/__init__.py
vizzy/vizzy.py
vizzy-0.3.0.dist-info/LICENSE
vizzy-0.3.0.dist-info/METADATA
vizzy-0.3.0.dist-info/WHEEL
vizzy-0.3.0.dist-info/top_level.txt
vizzy-0.3.0.dist-info/RECORD
