Metadata-Version: 2.1
Name: vizzy
Version: 0.3.0
Summary: Useful tools to visualize NLP data
Home-page: https://github.com/eanthony76
Download-URL: https://pypi.org/project/vizzy/
Author: Evan Anthony
Author-email: anthonyevanm@gmail.com
License: MIT
Keywords: EDA,visualization,NLP
License-File: LICENSE
Requires-Dist: pandas
Requires-Dist: matplotlib
Requires-Dist: numpy
Requires-Dist: nltk
Requires-Dist: seaborn
Requires-Dist: sklearn
Requires-Dist: gensim
Requires-Dist: pyldavis
Requires-Dist: wordcloud
Requires-Dist: textblob
Requires-Dist: spacy
Requires-Dist: textstat
Requires-Dist: scikit-learn
